kalite/__init__.py
kalite/application/__init__.py
kalite/application/config_driven_validations.py
kalite/application/default_metrics.py
kalite/data_classes/__init__.py
kalite/data_classes/meta_data.py
kalite/data_classes/metrics_data.py
kalite/data_classes/result_data.py
kalite/data_classes/validations_data.py
kalite/functions/__init__.py
kalite/functions/base.py
kalite/functions/metrics.py
kalite/functions/validations.py
kalite/functions/validator.py
kalite/utilities/__init__.py
kalite/utilities/logger.py
data_kalite-1.0.3.dist-info/METADATA
data_kalite-1.0.3.dist-info/WHEEL
data_kalite-1.0.3.dist-info/top_level.txt
data_kalite-1.0.3.dist-info/RECORD
