Metadata-Version: 2.1
Name: data-kalite
Version: 1.0.3
Summary: Data Quality for PySpark Pipelines
Author: Junaid Effendi
Requires-Python: >3.7.0,<3.11.0
Requires-Dist: dataclasses (==0.6)
Requires-Dist: great-expectations (==0.14.12)
Requires-Dist: inflection (==0.5.1)
Requires-Dist: pyspark (==3.2.0)
